Compiled from "ByteCodeSampleStaticString.java"
public class com.interview.javabasic.bytecode.ByteCodeSampleStaticString {
  static int k;

  static java.lang.String m;

  public com.interview.javabasic.bytecode.ByteCodeSampleStaticString();
    Code:
       0: aload_0
       1: invokespecial #1                  // Method java/lang/Object."<init>":()V
       4: return

  public static void main(java.lang.String[]);
    Code:
       0: ldc           #2                  // String abc
       2: putstatic     #3                  // Field m:Ljava/lang/String;
       5: iconst_5
       6: istore_2
       7: iconst_1
       8: istore_1
       9: iconst_3
      10: putstatic     #4                  // Field k:I
      13: new           #5                  // class java/lang/StringBuilder
      16: dup
      17: invokespecial #6                  // Method java/lang/StringBuilder."<init>":()V
      20: getstatic     #3                  // Field m:Ljava/lang/String;
      23: invokevirtual #7                  // Method java/lang/StringBuilder.append:(Ljava/lang/String;)Ljava/lang/StringBuilder;
      26: getstatic     #3                  // Field m:Ljava/lang/String;
      29: invokevirtual #7                  // Method java/lang/StringBuilder.append:(Ljava/lang/String;)Ljava/lang/StringBuilder;
      32: invokevirtual #8                  // Method java/lang/StringBuilder.toString:()Ljava/lang/String;
      35: putstatic     #3                  // Field m:Ljava/lang/String;
      38: getstatic     #4                  // Field k:I
      41: iconst_3
      42: imul
      43: putstatic     #4                  // Field k:I
      46: iinc          2, 1
      49: iinc          1, 1
      52: getstatic     #9                  // Field java/lang/System.out:Ljava/io/PrintStream;
      55: getstatic     #4                  // Field k:I
      58: invokevirtual #10                 // Method java/io/PrintStream.println:(I)V
      61: getstatic     #9                  // Field java/lang/System.out:Ljava/io/PrintStream;
      64: iload_2
      65: invokevirtual #10                 // Method java/io/PrintStream.println:(I)V
      68: getstatic     #9                  // Field java/lang/System.out:Ljava/io/PrintStream;
      71: iload_1
      72: invokevirtual #10                 // Method java/io/PrintStream.println:(I)V
      75: return
}